akre/create_akre_model.py
akre-0.1.11.dist-info/LICENSE.txt
akre-0.1.11.dist-info/METADATA
akre-0.1.11.dist-info/WHEEL
akre-0.1.11.dist-info/entry_points.txt
akre-0.1.11.dist-info/top_level.txt
akre-0.1.11.dist-info/RECORD
