Metadata-Version: 2.1
Name: akre
Version: 0.1.11
Summary: Boiler plate for creating an ML model
Home-page: https://github.com/elsatmr/akre-create-model.git
Download-URL: https://github.com/elsatmr/akre-create-model.git/archive/v_01.tar.gz
Author: Elsa Tamara
Author-email: elsaatamara@gmail.com
License: MIT
Keywords: machine_learning,model,boilerplate,ml
Classifier: Development Status :: 3 - Alpha
Classifier: Intended Audience :: Developers
Classifier: Topic :: Software Development :: Build Tools
Classifier: License :: OSI Approved :: MIT License
Classifier: Programming Language :: Python :: 3
Classifier: Programming Language :: Python :: 3.4
Classifier: Programming Language :: Python :: 3.5
Classifier: Programming Language :: Python :: 3.6
Classifier: Programming Language :: Python :: 3.7
Classifier: Programming Language :: Python :: 3.8
Classifier: Programming Language :: Python :: 3.9
License-File: LICENSE.txt
Requires-Dist: nbformat
